pygraph.py
pygraph_guozhiyao-0.1.0.dist-info/METADATA
pygraph_guozhiyao-0.1.0.dist-info/WHEEL
pygraph_guozhiyao-0.1.0.dist-info/RECORD
